pganonymize/__init__.py
pganonymize/__main__.py
pganonymize/cli.py
pganonymize/config.py
pganonymize/constants.py
pganonymize/exceptions.py
pganonymize/providers.py
pganonymize/utils.py
pganonymize/version.py
pganonymize-0.12.0.dist-info/LICENSE.rst
pganonymize-0.12.0.dist-info/METADATA
pganonymize-0.12.0.dist-info/WHEEL
pganonymize-0.12.0.dist-info/entry_points.txt
pganonymize-0.12.0.dist-info/top_level.txt
pganonymize-0.12.0.dist-info/RECORD
