Metadata-Version: 2.1
Name: pganonymize
Version: 0.12.0
Summary: Commandline tool to anonymize PostgreSQL databases
Home-page: https://github.com/rheinwerk-verlag/pganonymize
Author: Henning Kage
Author-email: henning.kage@rheinwerk-verlag.de
Maintainer: Henning Kage
Maintainer-email: henning.kage@rheinwerk-verlag.de
License: MIT license
Classifier: Development Status :: 4 - Beta
Classifier: Environment :: Console
Classifier: Intended Audience :: Developers
Classifier: License :: OSI Approved :: MIT License
Classifier: Natural Language :: English
Classifier: Operating System :: POSIX
Classifier: Programming Language :: Python
Classifier: Programming Language :: Python :: 2
Classifier: Programming Language :: Python :: 2.7
Classifier: Programming Language :: Python :: 3
Classifier: Programming Language :: Python :: 3.6
Classifier: Programming Language :: Python :: 3.7
Classifier: Programming Language :: Python :: 3.8
Classifier: Programming Language :: Python :: 3.9
Classifier: Programming Language :: Python :: 3.10
Classifier: Programming Language :: Python :: 3.11
Classifier: Programming Language :: Python :: 3.12
Classifier: Topic :: Database
License-File: LICENSE.rst
Requires-Dist: faker
Requires-Dist: pgcopy
Requires-Dist: psycopg2
Requires-Dist: pyyaml
Requires-Dist: tqdm
Requires-Dist: parmap ==1.5.2 ; python_version < "3.6"
Requires-Dist: pgcopy <1.6,>=1.5 ; python_version < "3.6"
Requires-Dist: psycopg2 <2.9,>=2.8.4 ; python_version < "3.6"
Requires-Dist: pyyaml <6.0,>=5.4.1 ; python_version < "3.6"
Requires-Dist: faker <4.0,>=3.0 ; python_version == "2.7"
Requires-Dist: parmap ; python_version >= "3.6"
